bunduk_mcp/__init__.py
bunduk_mcp/schemas.py
bunduk_mcp/server.py
bunduk_mcp/update.py
bunduk_mcp/util.py
bunduk_mcp/data/__init__.py
bunduk_mcp/data/loader.py
bunduk_mcp/data/manifest.json
bunduk_mcp/data/meta.py
bunduk_mcp/data/active/biogref-cbdb-data.csv
bunduk_mcp/data/active/biogref-ctext-data.csv
bunduk_mcp/data/active/biogref-ddbc-data.csv
bunduk_mcp/data/active/biogref-dnb-data.csv
bunduk_mcp/data/active/textref-cbeta-meta.csv
bunduk_mcp/data/active/textref-cbeta.csv
bunduk_mcp/data/active/textref-ctext-catalog.csv
bunduk_mcp/data/active/textref-ctext-meta.csv
bunduk_mcp/data/active/textref-kanripo-meta.csv
bunduk_mcp/data/active/textref-kanripo.csv
bunduk_mcp/references/biogref-cbdb-data.csv
bunduk_mcp/references/biogref-cbdb-meta.csv
bunduk_mcp/references/biogref-ctext-data.csv
bunduk_mcp/references/biogref-ctext-meta.csv
bunduk_mcp/references/biogref-ddbc-data.csv
bunduk_mcp/references/biogref-ddbc-meta.csv
bunduk_mcp/references/biogref-dnb-data.csv
bunduk_mcp/references/biogref-dnb-meta.csv
bunduk_mcp/references/biogref-schema.csv
bunduk_mcp/references/textref-cbeta-meta.csv
bunduk_mcp/references/textref-cbeta.csv
bunduk_mcp/references/textref-ctext-catalog.csv
bunduk_mcp/references/textref-ctext-meta.csv
bunduk_mcp/references/textref-kanripo-meta.csv
bunduk_mcp/references/textref-kanripo.csv
bunduk_mcp-0.2.1.dist-info/licenses/LICENSE
bunduk_mcp-0.2.1.dist-info/METADATA
bunduk_mcp-0.2.1.dist-info/WHEEL
bunduk_mcp-0.2.1.dist-info/entry_points.txt
bunduk_mcp-0.2.1.dist-info/top_level.txt
bunduk_mcp-0.2.1.dist-info/RECORD
