Metadata-Version: 2.4
Name: bunduk-mcp
Version: 0.2.1
Summary: MCP server for Chinese history study: BiogRef/TextRef CSVs, CBDB/TGAZ enrichments
Author-email: KL Tang <contact@kltang.net>
License-Expression: MIT
Project-URL: Bug Tracker, https://github.com/yourusername/bunduk-mcp/issues
Project-URL: Documentation, https://github.com/yourusername/bunduk-mcp#readme
Project-URL: Homepage, https://github.com/yourusername/bunduk-mcp
Project-URL: Repository, https://github.com/yourusername/bunduk-mcp
Keywords: mcp,chinese-history,cbdb,chgis,biographical-data,textual-references
Classifier: Development Status :: 4 - Beta
Classifier: Intended Audience :: Developers
Classifier: Intended Audience :: Science/Research
Classifier: Operating System :: OS Independent
Classifier: Programming Language :: Python :: 3
Classifier: Programming Language :: Python :: 3.10
Classifier: Programming Language :: Python :: 3.11
Classifier: Programming Language :: Python :: 3.12
Classifier: Programming Language :: Python :: 3.13
Classifier: Topic :: Scientific/Engineering :: Information Analysis
Classifier: Topic :: Text Processing :: Linguistic
Requires-Python: >=3.10
License-File: LICENSE
Requires-Dist: mcp>=0.1.0
Requires-Dist: pydantic>=2.6.0
Requires-Dist: httpx>=0.27.0
Dynamic: license-file
